stefano_models/__init__.py
stefano_models/mod/_glia__stefano_models__Golgi_hcn1__0.mod
stefano_models/mod/_glia__stefano_models__Golgi_hcn2__0.mod
stefano_models-0.0.1.data/data/mod/_glia__stefano_models__Golgi_hcn1__0.mod
stefano_models-0.0.1.data/data/mod/_glia__stefano_models__Golgi_hcn2__0.mod
stefano_models-0.0.1.dist-info/DESCRIPTION.rst
stefano_models-0.0.1.dist-info/METADATA
stefano_models-0.0.1.dist-info/RECORD
stefano_models-0.0.1.dist-info/WHEEL
stefano_models-0.0.1.dist-info/entry_points.txt
stefano_models-0.0.1.dist-info/metadata.json
stefano_models-0.0.1.dist-info/top_level.txt
