Metadata-Version: 2.0
Name: stefano-models
Version: 0.0.1
Summary: Glia package of NEURON models
Home-page: https://github.com/dbbs-lab/glia
Author: Stefano Casali
Author-email: stefano.casali@unipv.it
License: GPLv3
Platform: UNKNOWN
Classifier: Programming Language :: Python :: 3
Classifier: Operating System :: OS Independent
Requires-Dist: nrn-glia (>=0.0.1-a5)
